CHANGELOG.rst
CONTRIBUTORS.rst
chicken_dinner/__init__.py
chicken_dinner/__version__.py
chicken_dinner/assets/__init__.py
chicken_dinner/assets/dictionary.json
chicken_dinner/assets/dictionary.py
chicken_dinner/assets/maps/Baltic_Main_Low_Res.png
chicken_dinner/assets/maps/Desert_Main_Low_Res.png
chicken_dinner/assets/maps/DihorOtok_Main_Low_Res.png
chicken_dinner/assets/maps/Erangel_Main_Low_Res.png
chicken_dinner/assets/maps/Range_Main_Low_Res.png
chicken_dinner/assets/maps/Savage_Main_Low_Res.png
chicken_dinner/assets/maps.py
chicken_dinner/cli/__init__.py
chicken_dinner/cli/cli.py
chicken_dinner/constants.py
chicken_dinner/models/__init__.py
chicken_dinner/models/leaderboard.py
chicken_dinner/models/match/__init__.py
chicken_dinner/models/match/asset.py
chicken_dinner/models/match/match.py
chicken_dinner/models/match/participant.py
chicken_dinner/models/match/roster.py
chicken_dinner/models/player.py
chicken_dinner/models/player_season.py
chicken_dinner/models/players.py
chicken_dinner/models/samples.py
chicken_dinner/models/season.py
chicken_dinner/models/seasons.py
chicken_dinner/models/status.py
chicken_dinner/models/telemetry/__init__.py
chicken_dinner/models/telemetry/events.py
chicken_dinner/models/telemetry/objects.py
chicken_dinner/models/telemetry/telemetry.py
chicken_dinner/models/tournament.py
chicken_dinner/models/tournaments.py
chicken_dinner/pubgapi/__init__.py
chicken_dinner/pubgapi/core.py
chicken_dinner/pubgapi/pubg.py
chicken_dinner/util.py
chicken_dinner/visual/__init__.py
chicken_dinner/visual/playback.py
chicken_dinner-0.10.2.dist-info/entry_points.txt
chicken_dinner-0.10.2.dist-info/LICENSE.txt
chicken_dinner-0.10.2.dist-info/WHEEL
chicken_dinner-0.10.2.dist-info/METADATA
chicken_dinner-0.10.2.dist-info/RECORD
