Metadata-Version: 2.1
Name: chicken-dinner
Version: 0.10.2
Summary: PUBG JSON API Wrapper and Game Telemetry Visualizer
Home-page: https://github.com/crflynn/chicken-dinner
License: MIT
Keywords: pubg,api,animation,chicken,dinner
Author: Christopher Flynn
Author-email: crf204@gmail.com
Requires-Python: >=3.6,<4.0
Classifier: Development Status :: 4 - Beta
Classifier: License :: OSI Approved :: MIT License
Classifier: Programming Language :: Python
Classifier: Programming Language :: Python :: 3
Classifier: Programming Language :: Python :: 3.6
Classifier: Programming Language :: Python :: 3.7
Classifier: Programming Language :: Python :: Implementation :: CPython
Classifier: Topic :: Games/Entertainment
Classifier: Topic :: Games/Entertainment :: First Person Shooters
Classifier: Topic :: Software Development :: Libraries :: Python Modules
Provides-Extra: visual
Requires-Dist: click (>=7.0,<8.0)
Requires-Dist: matplotlib (>=3.1,<4.0); extra == "visual"
Requires-Dist: pillow (>=6.2,<7.0); extra == "visual"
Requires-Dist: requests (>=2.22,<3.0)
Requires-Dist: tabulate (>=0.8.3,<0.9.0)
Project-URL: Documentation, https://chicken-dinner.readthedocs.io/en/latest/
Project-URL: Repository, https://github.com/crflynn/chicken-dinner
